treesearch/__init__.py
treesearch/treesearch.abi3.so
treesearch/treesearch.pyi
treesearch_ud-0.2.0.dist-info/METADATA
treesearch_ud-0.2.0.dist-info/WHEEL
treesearch_ud-0.2.0.dist-info/licenses/LICENSE
treesearch_ud-0.2.0.dist-info/RECORD
