Metadata-Version: 2.4
Name: treesearch-ud
Version: 0.2.0
Classifier: Development Status :: 3 - Alpha
Classifier: Intended Audience :: Science/Research
Classifier: License :: OSI Approved :: MIT License
Classifier: Programming Language :: Python :: 3
Classifier: Programming Language :: Python :: 3.12
Classifier: Programming Language :: Python :: 3.13
Classifier: Programming Language :: Python :: 3.14
Classifier: Programming Language :: Python :: Implementation :: CPython
Classifier: Programming Language :: Rust
Classifier: Topic :: Text Processing :: Linguistic
Classifier: Typing :: Typed
Classifier: Operating System :: OS Independent
Requires-Dist: maturin>=1.10.1 ; extra == 'dev'
Requires-Dist: pytest>=9.0 ; extra == 'dev'
Requires-Dist: mkdocs>=1.5.0 ; extra == 'docs'
Requires-Dist: mkdocs-material>=9.0.0 ; extra == 'docs'
Requires-Dist: spacy>=3.0.0 ; extra == 'viz'
Provides-Extra: dev
Provides-Extra: docs
Provides-Extra: viz
License-File: LICENSE
Summary: High-performance toolkit for querying linguistic dependency parses
Keywords: nlp,linguistics,dependency-parsing,corpus-linguistics,treebank
Author-email: Rob Malouf <rmalouf@sdsu.edu>
License-Expression: MIT
Requires-Python: >=3.12
Project-URL: Documentation, https://rmalouf.github.io/treesearch/
Project-URL: Homepage, https://github.com/rmalouf/treesearch
Project-URL: Issues, https://github.com/rmalouf/treesearch/issues
Project-URL: Repository, https://github.com/rmalouf/treesearch
